[{"date":"2022\/02","stockCode":7131,"Name":"のむら産業　普通株式","englishName":"NOMURA CORPORATION","attribute":null,"attributeMemo":null,"attributeDate":null,"section":"JQS","sector":null,"margin-loan":"信用","tradingUnit":"100","open":"843.00","openDate":1.0,"high":"876.00","highDate":9.0,"low":"817.00","lowDate":24.0,"close":"840.00","closeDate":28.0,"averageClosingPrice":"849.89","tradingVolume":"88,000","tradingVolume-ToSTNeT":"900","tradingValue":"74,504,700","tradingValue-ToSTNeT":"758,700","daysTraded":"18"},{"date":"2022\/01","stockCode":7131,"Name":"のむら産業　普通株式","englishName":"NOMURA CORPORATION","attribute":null,"attributeMemo":null,"attributeDate":null,"section":"JQS","sector":null,"margin-loan":"信用","tradingUnit":"100","open":"888","openDate":4.0,"high":"898","highDate":17.0,"low":"825","lowDate":31.0,"close":"843","closeDate":31.0,"averageClosingPrice":"864.79","tradingVolume":"225,700","tradingVolume-ToSTNeT":"2,000","tradingValue":"194,836,300","tradingValue-ToSTNeT":"1,697,000","daysTraded":"19"},{"date":"2021\/12","stockCode":7131,"Name":"のむら産業　普通株式","englishName":"NOMURA CORPORATION","attribute":"新規上場  ","attributeMemo":"New Listing  ","attributeDate":"2021\/12\/02  ","section":"JQS","sector":null,"margin-loan":"信用","tradingUnit":"100","open":"1113","openDate":2.0,"high":"1125","highDate":3.0,"low":"857","lowDate":22.0,"close":"876","closeDate":30.0,"averageClosingPrice":"944.05","tradingVolume":"3399300","tradingVolume-ToSTNeT":"1200","tradingValue":"3488180650","tradingValue-ToSTNeT":"1135050","daysTraded":"21"},{"date":"2021\/11","stockCode":7131,"Name":"のむら産業　普通株式","englishName":"NOMURA CORPORATION","attribute":null,"attributeMemo":null,"attributeDate":null,"section":"JQS","sector":null,"margin-loan":"信用","tradingUnit":"100","open":"843","openDate":1.0,"high":"876","highDate":9.0,"low":"817","lowDate":24.0,"close":"840","closeDate":28.0,"averageClosingPrice":"849.89","tradingVolume":"88000","tradingVolume-ToSTNeT":"900","tradingValue":"74504700","tradingValue-ToSTNeT":"758700","daysTraded":"18"},{"date":"2021\/10","stockCode":7131,"Name":"のむら産業　普通株式","englishName":"NOMURA CORPORATION","attribute":null,"attributeMemo":null,"attributeDate":null,"section":"JQS","sector":null,"margin-loan":"信用","tradingUnit":"100","open":"888","openDate":4.0,"high":"898","highDate":17.0,"low":"825","lowDate":31.0,"close":"843","closeDate":31.0,"averageClosingPrice":"864.79","tradingVolume":"225,700","tradingVolume-ToSTNeT":"2,000","tradingValue":"194,836,300","tradingValue-ToSTNeT":"1,697,000","daysTraded":"19"},{"date":"2021\/09","stockCode":7131,"Name":"のむら産業　普通株式","englishName":"NOMURA CORPORATION","attribute":"新規上場  ","attributeMemo":"New Listing  ","attributeDate":"2021\/12\/02  ","section":"JQS","sector":null,"margin-loan":"信用","tradingUnit":"100","open":"1113","openDate":2.0,"high":"1125","highDate":3.0,"low":"857","lowDate":22.0,"close":"876","closeDate":30.0,"averageClosingPrice":"944.05","tradingVolume":"3399300","tradingVolume-ToSTNeT":"1200","tradingValue":"3488180650","tradingValue-ToSTNeT":"1135050","daysTraded":"21"},{"date":"2021\/08","stockCode":7131,"Name":"のむら産業　普通株式","englishName":"NOMURA CORPORATION","attribute":null,"attributeMemo":null,"attributeDate":null,"section":"JQS","sector":null,"margin-loan":"信用","tradingUnit":"100","open":"843","openDate":1.0,"high":"876","highDate":9.0,"low":"817","lowDate":24.0,"close":"840","closeDate":28.0,"averageClosingPrice":"849.89","tradingVolume":"88000","tradingVolume-ToSTNeT":"900","tradingValue":"74504700","tradingValue-ToSTNeT":"758700","daysTraded":"18"},{"date":"2021\/07","stockCode":7131,"Name":"のむら産業　普通株式","englishName":"NOMURA CORPORATION","attribute":null,"attributeMemo":null,"attributeDate":null,"section":"JQS","sector":null,"margin-loan":"信用","tradingUnit":"100","open":"888","openDate":4.0,"high":"898","highDate":17.0,"low":"825","lowDate":31.0,"close":"843","closeDate":31.0,"averageClosingPrice":"864.79","tradingVolume":"225700","tradingVolume-ToSTNeT":"2000","tradingValue":"194836300","tradingValue-ToSTNeT":"1697000","daysTraded":"19"},{"date":"2021\/06","stockCode":7131,"Name":"のむら産業　普通株式","englishName":"NOMURA CORPORATION","attribute":"新規上場  ","attributeMemo":"New Listing  ","attributeDate":"2021\/12\/02  ","section":"JQS","sector":null,"margin-loan":"信用","tradingUnit":"100","open":"1113","openDate":2.0,"high":"1125","highDate":3.0,"low":"857","lowDate":22.0,"close":"876","closeDate":30.0,"averageClosingPrice":"944.05","tradingVolume":"3399300","tradingVolume-ToSTNeT":"1200","tradingValue":"3488180650","tradingValue-ToSTNeT":"1135050","daysTraded":"21"},{"date":"2021\/05","stockCode":7131,"Name":"のむら産業　普通株式","englishName":"NOMURA CORPORATION","attribute":null,"attributeMemo":null,"attributeDate":null,"section":"JQS","sector":null,"margin-loan":"信用","tradingUnit":"100","open":"843","openDate":1.0,"high":"876","highDate":9.0,"low":"817","lowDate":24.0,"close":"840","closeDate":28.0,"averageClosingPrice":"849.89","tradingVolume":"88000","tradingVolume-ToSTNeT":"900","tradingValue":"74504700","tradingValue-ToSTNeT":"758700","daysTraded":"18"},{"date":"2021\/04","stockCode":7131,"Name":"のむら産業　普通株式","englishName":"NOMURA CORPORATION","attribute":null,"attributeMemo":null,"attributeDate":null,"section":"JQS","sector":null,"margin-loan":"信用","tradingUnit":"100","open":"888","openDate":4.0,"high":"898","highDate":17.0,"low":"825","lowDate":31.0,"close":"843","closeDate":31.0,"averageClosingPrice":"864.79","tradingVolume":"225,700","tradingVolume-ToSTNeT":"2,000","tradingValue":"194,836,300","tradingValue-ToSTNeT":"1,697,000","daysTraded":"19"},{"date":"2021\/03","stockCode":7131,"Name":"のむら産業　普通株式","englishName":"NOMURA CORPORATION","attribute":"新規上場  ","attributeMemo":"New Listing  ","attributeDate":"2021\/12\/02  ","section":"JQS","sector":null,"margin-loan":"信用","tradingUnit":"100","open":"1113","openDate":2.0,"high":"1125","highDate":3.0,"low":"857","lowDate":22.0,"close":"876","closeDate":30.0,"averageClosingPrice":"944.05","tradingVolume":"3399300","tradingVolume-ToSTNeT":"1200","tradingValue":"3488180650","tradingValue-ToSTNeT":"1135050","daysTraded":"21"},{"date":"2021\/02","stockCode":7131,"Name":"のむら産業　普通株式","englishName":"NOMURA CORPORATION","attribute":null,"attributeMemo":null,"attributeDate":null,"section":"JQS","sector":null,"margin-loan":"信用","tradingUnit":"100","open":"843","openDate":1.0,"high":"876","highDate":9.0,"low":"817","lowDate":24.0,"close":"840","closeDate":28.0,"averageClosingPrice":"849.89","tradingVolume":"88000","tradingVolume-ToSTNeT":"900","tradingValue":"74504700","tradingValue-ToSTNeT":"758700","daysTraded":"18"},{"date":"2021\/01","stockCode":7131,"Name":"のむら産業　普通株式","englishName":"NOMURA CORPORATION","attribute":null,"attributeMemo":null,"attributeDate":null,"section":"JQS","sector":null,"margin-loan":"信用","tradingUnit":"100","open":"888","openDate":4.0,"high":"898","highDate":17.0,"low":"825","lowDate":31.0,"close":"843","closeDate":31.0,"averageClosingPrice":"864.79","tradingVolume":"225700","tradingVolume-ToSTNeT":"2000","tradingValue":"194836300","tradingValue-ToSTNeT":"1697000","daysTraded":"19"},{"date":"2020\/12","stockCode":7131,"Name":"のむら産業　普通株式","englishName":"NOMURA CORPORATION","attribute":"新規上場  ","attributeMemo":"New Listing  ","attributeDate":"2021\/12\/02  ","section":"JQS","sector":null,"margin-loan":"信用","tradingUnit":"100","open":"1113","openDate":2.0,"high":"1125","highDate":3.0,"low":"857","lowDate":22.0,"close":"876","closeDate":30.0,"averageClosingPrice":"944.05","tradingVolume":"3399300","tradingVolume-ToSTNeT":"1200","tradingValue":"3488180650","tradingValue-ToSTNeT":"1135050","daysTraded":"21"},{"date":"2020\/11","stockCode":7131,"Name":"のむら産業　普通株式","englishName":"NOMURA CORPORATION","attribute":null,"attributeMemo":null,"attributeDate":null,"section":"JQS","sector":null,"margin-loan":"信用","tradingUnit":"100","open":"843","openDate":1.0,"high":"876","highDate":9.0,"low":"817","lowDate":24.0,"close":"840","closeDate":28.0,"averageClosingPrice":"849.89","tradingVolume":"88000","tradingVolume-ToSTNeT":"900","tradingValue":"74504700","tradingValue-ToSTNeT":"758700","daysTraded":"18"},{"date":"2020\/10","stockCode":7131,"Name":"のむら産業　普通株式","englishName":"NOMURA CORPORATION","attribute":null,"attributeMemo":null,"attributeDate":null,"section":"JQS","sector":null,"margin-loan":"信用","tradingUnit":"100","open":"888","openDate":4.0,"high":"898","highDate":17.0,"low":"825","lowDate":31.0,"close":"843","closeDate":31.0,"averageClosingPrice":"864.79","tradingVolume":"225700","tradingVolume-ToSTNeT":"2000","tradingValue":"194836300","tradingValue-ToSTNeT":"1697000","daysTraded":"19"},{"date":"2020\/09","stockCode":7131,"Name":"のむら産業　普通株式","englishName":"NOMURA CORPORATION","attribute":"新規上場  ","attributeMemo":"New Listing  ","attributeDate":"2021\/12\/02  ","section":"JQS","sector":null,"margin-loan":"信用","tradingUnit":100,"open":"1113","openDate":2.0,"high":"1125","highDate":3.0,"low":"857","lowDate":22.0,"close":"876","closeDate":30.0,"averageClosingPrice":"944.05","tradingVolume":"3399300","tradingVolume-ToSTNeT":"1200","tradingValue":"3488180650","tradingValue-ToSTNeT":"1135050","daysTraded":"21"},{"date":"2020\/08","stockCode":7131,"Name":"のむら産業　普通株式","englishName":"NOMURA CORPORATION","attribute":null,"attributeMemo":null,"attributeDate":null,"section":"JQS","sector":null,"margin-loan":"信用","tradingUnit":100,"open":"843","openDate":1.0,"high":"876","highDate":9.0,"low":"817","lowDate":24.0,"close":"840","closeDate":28.0,"averageClosingPrice":"849.89","tradingVolume":"88000","tradingVolume-ToSTNeT":"900","tradingValue":"74504700","tradingValue-ToSTNeT":"758700","daysTraded":"18"},{"date":"2020\/07","stockCode":7131,"Name":"のむら産業　普通株式","englishName":"NOMURA CORPORATION","attribute":null,"attributeMemo":null,"attributeDate":null,"section":"JQS","sector":null,"margin-loan":"信用","tradingUnit":100,"open":"888","openDate":4.0,"high":"898","highDate":17.0,"low":"825","lowDate":31.0,"close":"843","closeDate":31.0,"averageClosingPrice":"864.79","tradingVolume":"225700","tradingVolume-ToSTNeT":"2000","tradingValue":"194836300","tradingValue-ToSTNeT":"1697000","daysTraded":"19"},{"date":"2020\/06","stockCode":7131,"Name":"のむら産業　普通株式","englishName":"NOMURA CORPORATION","attribute":"新規上場  ","attributeMemo":"New Listing  ","attributeDate":"2021\/12\/02  ","section":"JQS","sector":null,"margin-loan":"信用","tradingUnit":100,"open":"1113","openDate":2.0,"high":"1125","highDate":3.0,"low":"857","lowDate":22.0,"close":"876","closeDate":30.0,"averageClosingPrice":"944.05","tradingVolume":"3399300","tradingVolume-ToSTNeT":"1200","tradingValue":"3488180650","tradingValue-ToSTNeT":"1135050","daysTraded":"21"},{"date":"2020\/05","stockCode":7131,"Name":"のむら産業　普通株式","englishName":"NOMURA CORPORATION","attribute":null,"attributeMemo":null,"attributeDate":null,"section":"JQS","sector":null,"margin-loan":"信用","tradingUnit":100,"open":"843","openDate":1.0,"high":"876","highDate":9.0,"low":"817","lowDate":24.0,"close":"840","closeDate":28.0,"averageClosingPrice":"849.89","tradingVolume":"88000","tradingVolume-ToSTNeT":"900","tradingValue":"74504700","tradingValue-ToSTNeT":"758700","daysTraded":"18"},{"date":"2020\/04","stockCode":7131,"Name":"のむら産業　普通株式","englishName":"NOMURA CORPORATION","attribute":null,"attributeMemo":null,"attributeDate":null,"section":"JQS","sector":null,"margin-loan":"信用","tradingUnit":100,"open":"888","openDate":4.0,"high":"898","highDate":17.0,"low":"825","lowDate":31.0,"close":"843","closeDate":31.0,"averageClosingPrice":"864.79","tradingVolume":"225700","tradingVolume-ToSTNeT":"2000","tradingValue":"194836300","tradingValue-ToSTNeT":"1697000","daysTraded":"19"},{"date":"2020\/03","stockCode":7131,"Name":"のむら産業　普通株式","englishName":"NOMURA CORPORATION","attribute":"新規上場  ","attributeMemo":"New Listing  ","attributeDate":"2021\/12\/02  ","section":"JQS","sector":null,"margin-loan":"信用","tradingUnit":100,"open":"1113","openDate":2.0,"high":"1125","highDate":3.0,"low":"857","lowDate":22.0,"close":"876","closeDate":30.0,"averageClosingPrice":"944.05","tradingVolume":"3399300","tradingVolume-ToSTNeT":"1200","tradingValue":"3488180650","tradingValue-ToSTNeT":"1135050","daysTraded":"21"},{"date":"2020\/02","stockCode":7131,"Name":"のむら産業　普通株式","englishName":"NOMURA CORPORATION","attribute":null,"attributeMemo":null,"attributeDate":null,"section":"JQS","sector":null,"margin-loan":"信用","tradingUnit":100,"open":"843","openDate":1.0,"high":"876","highDate":9.0,"low":"817","lowDate":24.0,"close":"840","closeDate":28.0,"averageClosingPrice":"849.89","tradingVolume":"88000","tradingVolume-ToSTNeT":"900","tradingValue":"74504700","tradingValue-ToSTNeT":"758700","daysTraded":"18"},{"date":"2020\/01","stockCode":7131,"Name":"のむら産業　普通株式","englishName":"NOMURA CORPORATION","attribute":null,"attributeMemo":null,"attributeDate":null,"section":"JQS","sector":null,"margin-loan":"信用","tradingUnit":100,"open":"888","openDate":4.0,"high":"898","highDate":17.0,"low":"825","lowDate":31.0,"close":"843","closeDate":31.0,"averageClosingPrice":"864.79","tradingVolume":"225700","tradingVolume-ToSTNeT":"2000","tradingValue":"194836300","tradingValue-ToSTNeT":"1697000","daysTraded":"19"},{"date":"2019\/12","stockCode":7131,"Name":"のむら産業　普通株式","englishName":"NOMURA CORPORATION","attribute":"新規上場  ","attributeMemo":"New Listing  ","attributeDate":"2021\/12\/02  ","section":"JQS","sector":null,"margin-loan":"信用","tradingUnit":100,"open":"1113","openDate":2.0,"high":"1125","highDate":3.0,"low":"857","lowDate":22.0,"close":"876","closeDate":30.0,"averageClosingPrice":"944.05","tradingVolume":"3399300","tradingVolume-ToSTNeT":"1200","tradingValue":"3488180650","tradingValue-ToSTNeT":"1135050","daysTraded":"21"},{"date":"2019\/11","stockCode":7131,"Name":"のむら産業　普通株式","englishName":"NOMURA CORPORATION","attribute":null,"attributeMemo":null,"attributeDate":null,"section":"JQS","sector":null,"margin-loan":"信用","tradingUnit":100,"open":"843","openDate":1.0,"high":"876","highDate":9.0,"low":"817","lowDate":24.0,"close":"840","closeDate":28.0,"averageClosingPrice":"849.89","tradingVolume":"88000","tradingVolume-ToSTNeT":"900","tradingValue":"74504700","tradingValue-ToSTNeT":"758700","daysTraded":"18"},{"date":"2019\/10","stockCode":7131,"Name":"のむら産業　普通株式","englishName":"NOMURA CORPORATION","attribute":null,"attributeMemo":null,"attributeDate":null,"section":"JQS","sector":null,"margin-loan":"信用","tradingUnit":100,"open":"888","openDate":4.0,"high":"898","highDate":17.0,"low":"825","lowDate":31.0,"close":"843","closeDate":31.0,"averageClosingPrice":"864.79","tradingVolume":"225700","tradingVolume-ToSTNeT":"2000","tradingValue":"194836300","tradingValue-ToSTNeT":"1697000","daysTraded":"19"},{"date":"2019\/09","stockCode":7131,"Name":"のむら産業　普通株式","englishName":"NOMURA CORPORATION","attribute":"新規上場  ","attributeMemo":"New Listing  ","attributeDate":"2021\/12\/02  ","section":"JQS","sector":null,"margin-loan":"信用","tradingUnit":100,"open":"1113","openDate":2.0,"high":"1125","highDate":3.0,"low":"857","lowDate":22.0,"close":"876","closeDate":30.0,"averageClosingPrice":"944.05","tradingVolume":"3399300","tradingVolume-ToSTNeT":"1200","tradingValue":"3488180650","tradingValue-ToSTNeT":"1135050","daysTraded":"21"},{"date":"2019\/08","stockCode":7131,"Name":"のむら産業　普通株式","englishName":"NOMURA CORPORATION","attribute":null,"attributeMemo":null,"attributeDate":null,"section":"JQS","sector":null,"margin-loan":"信用","tradingUnit":100,"open":"843","openDate":1.0,"high":"876","highDate":9.0,"low":"817","lowDate":24.0,"close":"840","closeDate":28.0,"averageClosingPrice":"849.89","tradingVolume":"88000","tradingVolume-ToSTNeT":"900","tradingValue":"74504700","tradingValue-ToSTNeT":"758700","daysTraded":"18"},{"date":"2019\/07","stockCode":7131,"Name":"のむら産業　普通株式","englishName":"NOMURA CORPORATION","attribute":null,"attributeMemo":null,"attributeDate":null,"section":"JQS","sector":null,"margin-loan":"信用","tradingUnit":100,"open":"888","openDate":4.0,"high":"898","highDate":17.0,"low":"825","lowDate":31.0,"close":"843","closeDate":31.0,"averageClosingPrice":"864.79","tradingVolume":"225700","tradingVolume-ToSTNeT":"2000","tradingValue":"194836300","tradingValue-ToSTNeT":"1697000","daysTraded":"19"},{"date":"2019\/06","stockCode":7131,"Name":"のむら産業　普通株式","englishName":"NOMURA CORPORATION","attribute":"新規上場  ","attributeMemo":"New Listing  ","attributeDate":"2021\/12\/02  ","section":"JQS","sector":null,"margin-loan":"信用","tradingUnit":100,"open":"1113","openDate":2.0,"high":"1125","highDate":3.0,"low":"857","lowDate":22.0,"close":"876","closeDate":30.0,"averageClosingPrice":"944.05","tradingVolume":"3399300","tradingVolume-ToSTNeT":"1200","tradingValue":"3488180650","tradingValue-ToSTNeT":"1135050","daysTraded":"21"},{"date":"2019\/05","stockCode":7131,"Name":"のむら産業　普通株式","englishName":"NOMURA CORPORATION","attribute":null,"attributeMemo":null,"attributeDate":null,"section":"JQS","sector":null,"margin-loan":"信用","tradingUnit":100,"open":"843","openDate":1.0,"high":"876","highDate":9.0,"low":"817","lowDate":24.0,"close":"840","closeDate":28.0,"averageClosingPrice":"849.89","tradingVolume":"88000","tradingVolume-ToSTNeT":"900","tradingValue":"74504700","tradingValue-ToSTNeT":"758700","daysTraded":"18"},{"date":"2019\/04","stockCode":7131,"Name":"のむら産業　普通株式","englishName":"NOMURA CORPORATION","attribute":null,"attributeMemo":null,"attributeDate":null,"section":"JQS","sector":null,"margin-loan":"信用","tradingUnit":100,"open":"888","openDate":4.0,"high":"898","highDate":17.0,"low":"825","lowDate":31.0,"close":"843","closeDate":31.0,"averageClosingPrice":"864.79","tradingVolume":"225700","tradingVolume-ToSTNeT":"2000","tradingValue":"194836300","tradingValue-ToSTNeT":"1697000","daysTraded":"19"},{"date":"2019\/03","stockCode":7131,"Name":"のむら産業　普通株式","englishName":"NOMURA CORPORATION","attribute":"新規上場  ","attributeMemo":"New Listing  ","attributeDate":"2021\/12\/02  ","section":"JQS","sector":null,"margin-loan":"信用","tradingUnit":100,"open":"1113","openDate":2.0,"high":"1125","highDate":3.0,"low":"857","lowDate":22.0,"close":"876","closeDate":30.0,"averageClosingPrice":"944.05","tradingVolume":"3399300","tradingVolume-ToSTNeT":"1200","tradingValue":"3488180650","tradingValue-ToSTNeT":"1135050","daysTraded":"21"},{"date":"2019\/02","stockCode":7131,"Name":"のむら産業　普通株式","englishName":"NOMURA CORPORATION","attribute":null,"attributeMemo":null,"attributeDate":null,"section":"JQS","sector":null,"margin-loan":"信用","tradingUnit":100,"open":"843","openDate":1.0,"high":"876","highDate":9.0,"low":"817","lowDate":24.0,"close":"840","closeDate":28.0,"averageClosingPrice":"849.89","tradingVolume":"88000","tradingVolume-ToSTNeT":"900","tradingValue":"74504700","tradingValue-ToSTNeT":"758700","daysTraded":"18"},{"date":"2019\/01","stockCode":7131,"Name":"のむら産業　普通株式","englishName":"NOMURA CORPORATION","attribute":null,"attributeMemo":null,"attributeDate":null,"section":"JQS","sector":null,"margin-loan":"信用","tradingUnit":100,"open":"888","openDate":4.0,"high":"898","highDate":17.0,"low":"825","lowDate":31.0,"close":"843","closeDate":31.0,"averageClosingPrice":"864.79","tradingVolume":"225700","tradingVolume-ToSTNeT":"2000","tradingValue":"194836300","tradingValue-ToSTNeT":"1697000","daysTraded":"19"},{"date":"2018\/12","stockCode":7131,"Name":"のむら産業　普通株式","englishName":"NOMURA CORPORATION","attribute":"新規上場  ","attributeMemo":"New Listing  ","attributeDate":"2021\/12\/02  ","section":"JQS","sector":null,"margin-loan":"信用","tradingUnit":100,"open":"1113","openDate":2.0,"high":"1125","highDate":3.0,"low":"857","lowDate":22.0,"close":"876","closeDate":30.0,"averageClosingPrice":"944.05","tradingVolume":"3399300","tradingVolume-ToSTNeT":"1200","tradingValue":"3488180650","tradingValue-ToSTNeT":"1135050","daysTraded":"21"},{"date":"2018\/11","stockCode":7131,"Name":"のむら産業　普通株式","englishName":"NOMURA CORPORATION","attribute":null,"attributeMemo":null,"attributeDate":null,"section":"JQS","sector":null,"margin-loan":"信用","tradingUnit":100,"open":"843","openDate":1.0,"high":"876","highDate":9.0,"low":"817","lowDate":24.0,"close":"840","closeDate":28.0,"averageClosingPrice":"849.89","tradingVolume":"88000","tradingVolume-ToSTNeT":"900","tradingValue":"74504700","tradingValue-ToSTNeT":"758700","daysTraded":"18"},{"date":"2018\/10","stockCode":7131,"Name":"のむら産業　普通株式","englishName":"NOMURA CORPORATION","attribute":null,"attributeMemo":null,"attributeDate":null,"section":"JQS","sector":null,"margin-loan":"信用","tradingUnit":100,"open":"888","openDate":4.0,"high":"898","highDate":17.0,"low":"825","lowDate":31.0,"close":"843","closeDate":31.0,"averageClosingPrice":"864.79","tradingVolume":"225700","tradingVolume-ToSTNeT":"2000","tradingValue":"194836300","tradingValue-ToSTNeT":"1697000","daysTraded":"19"},{"date":"2018\/09","stockCode":7131,"Name":"のむら産業　普通株式","englishName":"NOMURA CORPORATION","attribute":"新規上場  ","attributeMemo":"New Listing  ","attributeDate":"2021\/12\/02  ","section":"JQS","sector":null,"margin-loan":"信用","tradingUnit":100,"open":"1113","openDate":2.0,"high":"1125","highDate":3.0,"low":"857","lowDate":22.0,"close":"876","closeDate":30.0,"averageClosingPrice":"944.05","tradingVolume":"3399300","tradingVolume-ToSTNeT":"1200","tradingValue":"3488180650","tradingValue-ToSTNeT":"1135050","daysTraded":"21"},{"date":"2018\/08","stockCode":7131,"Name":"のむら産業　普通株式","englishName":"NOMURA CORPORATION","attribute":null,"attributeMemo":null,"attributeDate":null,"section":"JQS","sector":null,"margin-loan":"信用","tradingUnit":100,"open":"843","openDate":1.0,"high":"876","highDate":9.0,"low":"817","lowDate":24.0,"close":"840","closeDate":28.0,"averageClosingPrice":"849.89","tradingVolume":"88000","tradingVolume-ToSTNeT":"900","tradingValue":"74504700","tradingValue-ToSTNeT":"758700","daysTraded":"18"},{"date":"2018\/07","stockCode":7131,"Name":"のむら産業　普通株式","englishName":"NOMURA CORPORATION","attribute":null,"attributeMemo":null,"attributeDate":null,"section":"JQS","sector":null,"margin-loan":"信用","tradingUnit":100,"open":"888","openDate":4.0,"high":"898","highDate":17.0,"low":"825","lowDate":31.0,"close":"843","closeDate":31.0,"averageClosingPrice":"864.79","tradingVolume":"225700","tradingVolume-ToSTNeT":"2000","tradingValue":"194836300","tradingValue-ToSTNeT":"1697000","daysTraded":"19"},{"date":"2018\/06","stockCode":7131,"Name":"のむら産業　普通株式","englishName":"NOMURA CORPORATION","attribute":"新規上場  ","attributeMemo":"New Listing  ","attributeDate":"2021\/12\/02  ","section":"JQS","sector":null,"margin-loan":"信用","tradingUnit":100,"open":"1113","openDate":2.0,"high":"1125","highDate":3.0,"low":"857","lowDate":22.0,"close":"876","closeDate":30.0,"averageClosingPrice":"944.05","tradingVolume":"3399300","tradingVolume-ToSTNeT":"1200","tradingValue":"3488180650","tradingValue-ToSTNeT":"1135050","daysTraded":"21"},{"date":"2018\/05","stockCode":7131,"Name":"のむら産業　普通株式","englishName":"NOMURA CORPORATION","attribute":null,"attributeMemo":null,"attributeDate":null,"section":"JQS","sector":null,"margin-loan":"信用","tradingUnit":100,"open":"843","openDate":1.0,"high":"876","highDate":9.0,"low":"817","lowDate":24.0,"close":"840","closeDate":28.0,"averageClosingPrice":"849.89","tradingVolume":"88000","tradingVolume-ToSTNeT":"900","tradingValue":"74504700","tradingValue-ToSTNeT":"758700","daysTraded":"18"},{"date":"2018\/04","stockCode":7131,"Name":"のむら産業　普通株式","englishName":"NOMURA CORPORATION","attribute":null,"attributeMemo":null,"attributeDate":null,"section":"JQS","sector":null,"margin-loan":"信用","tradingUnit":100,"open":"888","openDate":4.0,"high":"898","highDate":17.0,"low":"825","lowDate":31.0,"close":"843","closeDate":31.0,"averageClosingPrice":"864.79","tradingVolume":"225700","tradingVolume-ToSTNeT":"2000","tradingValue":"194836300","tradingValue-ToSTNeT":"1697000","daysTraded":"19"},{"date":"2018\/03","stockCode":7131,"Name":"のむら産業　普通株式","englishName":"NOMURA CORPORATION","attribute":"新規上場  ","attributeMemo":"New Listing  ","attributeDate":"2021\/12\/02  ","section":"JQS","sector":null,"margin-loan":"信用","tradingUnit":100,"open":"1113","openDate":2.0,"high":"1125","highDate":3.0,"low":"857","lowDate":22.0,"close":"876","closeDate":30.0,"averageClosingPrice":"944.05","tradingVolume":"3399300","tradingVolume-ToSTNeT":"1200","tradingValue":"3488180650","tradingValue-ToSTNeT":"1135050","daysTraded":"21"},{"date":"2018\/02","stockCode":7131,"Name":"のむら産業　普通株式","englishName":"NOMURA CORPORATION","attribute":null,"attributeMemo":null,"attributeDate":null,"section":"JQS","sector":null,"margin-loan":"信用","tradingUnit":100,"open":"843","openDate":1.0,"high":"876","highDate":9.0,"low":"817","lowDate":24.0,"close":"840","closeDate":28.0,"averageClosingPrice":"849.89","tradingVolume":"88000","tradingVolume-ToSTNeT":"900","tradingValue":"74504700","tradingValue-ToSTNeT":"758700","daysTraded":"18"},{"date":"2018\/01","stockCode":7131,"Name":"のむら産業　普通株式","englishName":"NOMURA CORPORATION","attribute":null,"attributeMemo":null,"attributeDate":null,"section":"JQS","sector":null,"margin-loan":"信用","tradingUnit":100,"open":"888","openDate":4.0,"high":"898","highDate":17.0,"low":"825","lowDate":31.0,"close":"843","closeDate":31.0,"averageClosingPrice":"864.79","tradingVolume":"225700","tradingVolume-ToSTNeT":"2000","tradingValue":"194836300","tradingValue-ToSTNeT":"1697000","daysTraded":"19"},{"date":"2017\/12","stockCode":7131,"Name":"のむら産業　普通株式","englishName":"NOMURA CORPORATION","attribute":"新規上場  ","attributeMemo":"New Listing  ","attributeDate":"2021\/12\/02  ","section":"JQS","sector":null,"margin-loan":"信用","tradingUnit":100,"open":"1113","openDate":2.0,"high":"1125","highDate":3.0,"low":"857","lowDate":22.0,"close":"876","closeDate":30.0,"averageClosingPrice":"944.05","tradingVolume":"3399300","tradingVolume-ToSTNeT":"1200","tradingValue":"3488180650","tradingValue-ToSTNeT":"1135050","daysTraded":"21"},{"date":"2017\/11","stockCode":7131,"Name":"のむら産業　普通株式","englishName":"NOMURA CORPORATION","attribute":null,"attributeMemo":null,"attributeDate":null,"section":"JQS","sector":null,"margin-loan":"信用","tradingUnit":100,"open":"843","openDate":1.0,"high":"876","highDate":9.0,"low":"817","lowDate":24.0,"close":"840","closeDate":28.0,"averageClosingPrice":"849.89","tradingVolume":"88000","tradingVolume-ToSTNeT":"900","tradingValue":"74504700","tradingValue-ToSTNeT":"758700","daysTraded":"18"},{"date":"2017\/10","stockCode":7131,"Name":"のむら産業　普通株式","englishName":"NOMURA CORPORATION","attribute":null,"attributeMemo":null,"attributeDate":null,"section":"JQS","sector":null,"margin-loan":"信用","tradingUnit":100,"open":"888","openDate":4.0,"high":"898","highDate":17.0,"low":"825","lowDate":31.0,"close":"843","closeDate":31.0,"averageClosingPrice":"864.79","tradingVolume":"225700","tradingVolume-ToSTNeT":"2000","tradingValue":"194836300","tradingValue-ToSTNeT":"1697000","daysTraded":"19"},{"date":"2017\/09","stockCode":7131,"Name":"のむら産業　普通株式","englishName":"NOMURA CORPORATION","attribute":"新規上場  ","attributeMemo":"New Listing  ","attributeDate":"2021\/12\/02  ","section":"JQS","sector":null,"margin-loan":"信用","tradingUnit":100,"open":"1113","openDate":2.0,"high":"1125","highDate":3.0,"low":"857","lowDate":22.0,"close":"876","closeDate":30.0,"averageClosingPrice":"944.05","tradingVolume":"3399300","tradingVolume-ToSTNeT":"1200","tradingValue":"3488180650","tradingValue-ToSTNeT":"1135050","daysTraded":"21"},{"date":"2017\/08","stockCode":7131,"Name":"のむら産業　普通株式","englishName":"NOMURA CORPORATION","attribute":null,"attributeMemo":null,"attributeDate":null,"section":"JQS","sector":null,"margin-loan":"信用","tradingUnit":100,"open":"843","openDate":1.0,"high":"876","highDate":9.0,"low":"817","lowDate":24.0,"close":"840","closeDate":28.0,"averageClosingPrice":"849.89","tradingVolume":"88000","tradingVolume-ToSTNeT":"900","tradingValue":"74504700","tradingValue-ToSTNeT":"758700","daysTraded":"18"},{"date":"2017\/07","stockCode":7131,"Name":"のむら産業　普通株式","englishName":"NOMURA CORPORATION","attribute":null,"attributeMemo":null,"attributeDate":null,"section":"JQS","sector":null,"margin-loan":"信用","tradingUnit":100,"open":"888","openDate":4.0,"high":"898","highDate":17.0,"low":"825","lowDate":31.0,"close":"843","closeDate":31.0,"averageClosingPrice":"864.79","tradingVolume":"225700","tradingVolume-ToSTNeT":"2000","tradingValue":"194836300","tradingValue-ToSTNeT":"1697000","daysTraded":"19"},{"date":"2017\/06","stockCode":7131,"Name":"のむら産業　普通株式","englishName":"NOMURA CORPORATION","attribute":"新規上場  ","attributeMemo":"New Listing  ","attributeDate":"2021\/12\/02  ","section":"JQS","sector":null,"margin-loan":"信用","tradingUnit":100,"open":"1113","openDate":2.0,"high":"1125","highDate":3.0,"low":"857","lowDate":22.0,"close":"876","closeDate":30.0,"averageClosingPrice":"944.05","tradingVolume":"3399300","tradingVolume-ToSTNeT":"1200","tradingValue":"3488180650","tradingValue-ToSTNeT":"1135050","daysTraded":"21"},{"date":"2017\/05","stockCode":7131,"Name":"のむら産業　普通株式","englishName":"NOMURA CORPORATION","attribute":null,"attributeMemo":null,"attributeDate":null,"section":"JQS","sector":null,"margin-loan":"信用","tradingUnit":100,"open":"843","openDate":1.0,"high":"876","highDate":9.0,"low":"817","lowDate":24.0,"close":"840","closeDate":28.0,"averageClosingPrice":"849.89","tradingVolume":"88000","tradingVolume-ToSTNeT":"900","tradingValue":"74504700","tradingValue-ToSTNeT":"758700","daysTraded":"18"},{"date":"2017\/04","stockCode":7131,"Name":"のむら産業　普通株式","englishName":"NOMURA CORPORATION","attribute":null,"attributeMemo":null,"attributeDate":null,"section":"JQS","sector":null,"margin-loan":"信用","tradingUnit":100,"open":"888","openDate":4.0,"high":"898","highDate":17.0,"low":"825","lowDate":31.0,"close":"843","closeDate":31.0,"averageClosingPrice":"864.79","tradingVolume":"225700","tradingVolume-ToSTNeT":"2000","tradingValue":"194836300","tradingValue-ToSTNeT":"1697000","daysTraded":"19"},{"date":"2017\/03","stockCode":7131,"Name":"のむら産業　普通株式","englishName":"NOMURA CORPORATION","attribute":"新規上場  ","attributeMemo":"New Listing  ","attributeDate":"2021\/12\/02  ","section":"JQS","sector":null,"margin-loan":"信用","tradingUnit":100,"open":"1113","openDate":2.0,"high":"1125","highDate":3.0,"low":"857","lowDate":22.0,"close":"876","closeDate":30.0,"averageClosingPrice":"944.05","tradingVolume":"3399300","tradingVolume-ToSTNeT":"1200","tradingValue":"3488180650","tradingValue-ToSTNeT":"1135050","daysTraded":"21"}]