[{"Assets_0_Q1_USD":10245419000.0,"CommonStockSharesOutstanding_0_Q1_shares":44060957.0,"EarningsPerShareBasic_1_Q1_USD":0.76,"EarningsPerShareDiluted_1_Q1_USD":0.76,"NetIncomeLoss_1_Q1_USD":33529000.0,"PaymentsOfDividendsCommonStock_1_Q1_USD":11450000.0,"StockholdersEquity_0_Q1_USD":1403026000.0,"WeightedAverageNumberOfDilutedSharesOutstanding_1_Q1_shares":44168242.0,"WeightedAverageNumberOfSharesOutstandingBasic_1_Q1_shares":44050701.0,"Ticker":"WSBC","CIK":"203596","name":"WESBANCO INC","OfficialName":"WesBanco Inc. Common Stock","form":"10-Q","period":"20180331","fy":"2018.0","fp":"Q1","qtrs":"0","uom":"USD","footnote":"nan","Market Cap":"2351528309.0","Country":"United States","Sector":"Finance","Industry":"Major Banks","Market":"NASDAQ","SP500":"nan","filed":"20180430"}]