[{"edinetCode":"E04254","stockCode":"9171","submitDate":"2017\/6\/29","endDate":"2017\/3\/31","numberOfEmployee":992.0,"averageTemporaryStaff":null,"sharesOwned":8487000.0,"sharesOwendPercent":0.6662,"numberOfSubsidiary":13.0,"bps":1165.54,"equityRatio":0.277,"cashAndCashEquivalents":6663753000.0,"assets":52900591000.0,"currentAssets":17128793000.0,"fixedAsset":35723059000.0,"tangibleFixedAssets":24343291000.0,"intangibleFixedAssets":1364266000.0,"investmentAndOtherAssets":10015500000.0,"liabilities":35251092000.0,"currentLiabilities":17064144000.0,"shorTermDept":4761260000.0,"currentPortionOfBonds":1098160000.0,"currentPortionOfLongTermDebt":1889488000.0,"fixedLiabilities":18186947000.0,"bonds":2121360000.0,"convertibleBond":null,"commercialPaper":null,"longTermDebts":6078128000.0,"netAsset":17649499000.0,"capitalStock":11921952000.0,"capital":1215035000.0,"capitalSurplus":943661000.0,"accumulatedEarnings":9802950000.0,"treasuryStock":-39694000.0,"valuationAndConversionAdjustments":2753837000.0,"Sales":44358375000.0,"costOfSales":35638325000.0,"grossProfit":8720049000.0,"sgaExpenses":6398981000.0,"salaryAndBenefit":null,"depreciationAndSGA":370108000.0,"RDExpenses":null,"operatingIncome":2321068000.0,"nonOperatingIncome":449827000.0,"nonOperatingExpenses":396935000.0,"interestExpense":316626000.0,"ordinaryProfit":2373959000.0,"extraordinaryGain":44601000.0,"extraordinaryLoss":535608000.0,"incomeBeforeTax":1882952000.0,"incomeTaxes":749980000.0,"netIncome":1132972000.0,"netIncomeAttributableToOwnersOfTheParentCompany":910662000.0,"comprehensiveIncome":1910671000.0,"eps":72.31,"dilutedEps":null,"per":6.3,"roe":0.066,"cashFlowFromOperatingActivities":5089382000.0,"depreciationAndCashflowFromOperatingActivities":2735167000.0,"cashFlowFromInvestingActivities":-981844000.0,"cashFlowFromFinancialActivities":-4253031000.0,"changesInCashAndCashEquivalents":-145642000.0,"previousYearAsset":54236326000.0,"previousYearSales":44387182000.0,"previousYearNetIncome":1242420000.0,"averageAge":null,"averageYearsOfService":null,"averageAnnualSalary":null,"outstandingShares":12739696.0,"dividendPerShare":6.0,"grossProfit2":8720050000.0,"grossProfitMargin":0.196581818,"operatingProfitMargin":0.052325361,"recurringProfitRatio":0.053517718,"SGAtoSalesRatio":0.144256434,"totalAssetTurnover":0.838523241,"currentRatio":1.003788587,"salesRateOfChange":-0.000648994,"netIncomeRageOfChange":-0.088092593,"averageAssetsThisYear":53568458500.0,"totalAssetOrdinaryRateOfReturn":0.044316358," totalAssetNetProfitMargin":0.021149983,"totalAssetsNetProfitmarginAttributableToOwnersOfTheParentCompany":0.016999967,"equityCapital":14675789000.0,"interestBearingDebt":15948396000.0,"companyName":"栗林商船","industry":"海運業"},{"edinetCode":"E04254","stockCode":"9171","submitDate":"2018\/6\/28","endDate":"2018\/3\/31","numberOfEmployee":1004.0,"averageTemporaryStaff":null,"sharesOwned":8237000.0,"sharesOwendPercent":0.6543,"numberOfSubsidiary":13.0,"bps":1372.45,"equityRatio":0.314,"cashAndCashEquivalents":6716257000.0,"assets":54994172000.0,"currentAssets":17407178000.0,"fixedAsset":37556456000.0,"tangibleFixedAssets":24182007000.0,"intangibleFixedAssets":1305967000.0,"investmentAndOtherAssets":12068481000.0,"liabilities":34563353000.0,"currentLiabilities":17895969000.0,"shorTermDept":5780284000.0,"currentPortionOfBonds":1143160000.0,"currentPortionOfLongTermDebt":2283227000.0,"fixedLiabilities":16667383000.0,"bonds":978200000.0,"convertibleBond":null,"commercialPaper":null,"longTermDebts":5619903000.0,"netAsset":20430819000.0,"capitalStock":13484469000.0,"capital":1215035000.0,"capitalSurplus":946704000.0,"accumulatedEarnings":11364082000.0,"treasuryStock":-41351000.0,"valuationAndConversionAdjustments":3791995000.0,"Sales":45969925000.0,"costOfSales":37487190000.0,"grossProfit":8482734000.0,"sgaExpenses":6594272000.0,"salaryAndBenefit":null,"depreciationAndSGA":379538000.0,"RDExpenses":null,"operatingIncome":1888462000.0,"nonOperatingIncome":477911000.0,"nonOperatingExpenses":360213000.0,"interestExpense":265361000.0,"ordinaryProfit":2006160000.0,"extraordinaryGain":558055000.0,"extraordinaryLoss":180524000.0,"incomeBeforeTax":2383691000.0,"incomeTaxes":694339000.0,"netIncome":1689351000.0,"netIncomeAttributableToOwnersOfTheParentCompany":1529330000.0,"comprehensiveIncome":2763048000.0,"eps":121.48,"dilutedEps":null,"per":5.1,"roe":0.096,"cashFlowFromOperatingActivities":3046762000.0,"depreciationAndCashflowFromOperatingActivities":2614082000.0,"cashFlowFromInvestingActivities":-1942891000.0,"cashFlowFromFinancialActivities":-1050766000.0,"changesInCashAndCashEquivalents":52503000.0,"previousYearAsset":52900591000.0,"previousYearSales":44358375000.0,"previousYearNetIncome":1132972000.0,"averageAge":null,"averageYearsOfService":null,"averageAnnualSalary":null,"outstandingShares":12739696.0,"dividendPerShare":6.0,"grossProfit2":8482735000.0,"grossProfitMargin":0.184527928,"operatingProfitMargin":0.04108038,"recurringProfitRatio":0.043640706,"SGAtoSalesRatio":0.143447526,"totalAssetTurnover":0.835905394,"currentRatio":0.972687089,"salesRateOfChange":0.036330231,"netIncomeRageOfChange":0.491079215,"averageAssetsThisYear":53947381500.0,"totalAssetOrdinaryRateOfReturn":0.037187347," totalAssetNetProfitMargin":0.031314791,"totalAssetsNetProfitmarginAttributableToOwnersOfTheParentCompany":0.028348549,"equityCapital":17276464000.0,"interestBearingDebt":15804774000.0,"companyName":"栗林商船","industry":"海運業"},{"edinetCode":"E04254","stockCode":"9171","submitDate":"2019\/6\/27","endDate":"2019\/3\/31","numberOfEmployee":1038.0,"averageTemporaryStaff":null,"sharesOwned":8237000.0,"sharesOwendPercent":0.6543,"numberOfSubsidiary":13.0,"bps":1448.24,"equityRatio":0.32,"cashAndCashEquivalents":7655813000.0,"assets":56935226000.0,"currentAssets":18657990000.0,"fixedAsset":38252062000.0,"tangibleFixedAssets":25546488000.0,"intangibleFixedAssets":1261598000.0,"investmentAndOtherAssets":11443975000.0,"liabilities":35482848000.0,"currentLiabilities":17033772000.0,"shorTermDept":4721481000.0,"currentPortionOfBonds":623160000.0,"currentPortionOfLongTermDebt":2405042000.0,"fixedLiabilities":18449076000.0,"bonds":1135040000.0,"convertibleBond":null,"commercialPaper":null,"longTermDebts":7841454000.0,"netAsset":21452378000.0,"capitalStock":15046028000.0,"capital":1215035000.0,"capitalSurplus":946704000.0,"accumulatedEarnings":12926312000.0,"treasuryStock":-42023000.0,"valuationAndConversionAdjustments":3182874000.0,"Sales":47588160000.0,"costOfSales":39249967000.0,"grossProfit":8338193000.0,"sgaExpenses":6613298000.0,"salaryAndBenefit":null,"depreciationAndSGA":357033000.0,"RDExpenses":null,"operatingIncome":1724894000.0,"nonOperatingIncome":555873000.0,"nonOperatingExpenses":354415000.0,"interestExpense":235788000.0,"ordinaryProfit":1926352000.0,"extraordinaryGain":469257000.0,"extraordinaryLoss":1833000.0,"incomeBeforeTax":2393776000.0,"incomeTaxes":621558000.0,"netIncome":1772218000.0,"netIncomeAttributableToOwnersOfTheParentCompany":1637758000.0,"comprehensiveIncome":1110099000.0,"eps":130.11,"dilutedEps":null,"per":3.3,"roe":0.092,"cashFlowFromOperatingActivities":4305326000.0,"depreciationAndCashflowFromOperatingActivities":2373239000.0,"cashFlowFromInvestingActivities":-3557534000.0,"cashFlowFromFinancialActivities":192070000.0,"changesInCashAndCashEquivalents":939555000.0,"previousYearAsset":54966229000.0,"previousYearSales":45969925000.0,"previousYearNetIncome":1689351000.0,"averageAge":41.6,"averageYearsOfService":15.4,"averageAnnualSalary":6990000.0,"outstandingShares":12739696.0,"dividendPerShare":12.0,"grossProfit2":8338193000.0,"grossProfitMargin":0.175215705,"operatingProfitMargin":0.036246285,"recurringProfitRatio":0.040479649,"SGAtoSalesRatio":0.138969399,"totalAssetTurnover":0.835829825,"currentRatio":1.095352809,"salesRateOfChange":0.035202037,"netIncomeRageOfChange":0.049052565,"averageAssetsThisYear":55950727500.0,"totalAssetOrdinaryRateOfReturn":0.034429436," totalAssetNetProfitMargin":0.031674619,"totalAssetsNetProfitmarginAttributableToOwnersOfTheParentCompany":0.029271434,"equityCapital":18228902000.0,"interestBearingDebt":16726177000.0,"companyName":"栗林商船","industry":"海運業"},{"edinetCode":"E04254","stockCode":"9171","submitDate":"2020\/6\/26","endDate":"2020\/3\/31","numberOfEmployee":1040.0,"averageTemporaryStaff":null,"sharesOwned":8255000.0,"sharesOwendPercent":0.6531,"numberOfSubsidiary":13.0,"bps":1385.06,"equityRatio":0.274,"cashAndCashEquivalents":8120146000.0,"assets":63859927000.0,"currentAssets":19456049000.0,"fixedAsset":44385997000.0,"tangibleFixedAssets":33171552000.0,"intangibleFixedAssets":1271041000.0,"investmentAndOtherAssets":9943403000.0,"liabilities":43181955000.0,"currentLiabilities":17721051000.0,"shorTermDept":5585104000.0,"currentPortionOfBonds":455040000.0,"currentPortionOfLongTermDebt":2673683000.0,"fixedLiabilities":25460904000.0,"bonds":1040000000.0,"convertibleBond":null,"commercialPaper":null,"longTermDebts":11888581000.0,"netAsset":20677971000.0,"capitalStock":15364667000.0,"capital":1215035000.0,"capitalSurplus":971090000.0,"accumulatedEarnings":13205834000.0,"treasuryStock":-27293000.0,"valuationAndConversionAdjustments":2143248000.0,"Sales":45991467000.0,"costOfSales":38703924000.0,"grossProfit":7287542000.0,"sgaExpenses":6849750000.0,"salaryAndBenefit":null,"depreciationAndSGA":392382000.0,"RDExpenses":null,"operatingIncome":437792000.0,"nonOperatingIncome":527026000.0,"nonOperatingExpenses":280099000.0,"interestExpense":232988000.0,"ordinaryProfit":684719000.0,"extraordinaryGain":241832000.0,"extraordinaryLoss":143031000.0,"incomeBeforeTax":783520000.0,"incomeTaxes":336450000.0,"netIncome":447070000.0,"netIncomeAttributableToOwnersOfTheParentCompany":430565000.0,"comprehensiveIncome":-631416000.0,"eps":34.12,"dilutedEps":null,"per":9.1,"roe":0.024,"cashFlowFromOperatingActivities":1843410000.0,"depreciationAndCashflowFromOperatingActivities":2350596000.0,"cashFlowFromInvestingActivities":-9510483000.0,"cashFlowFromFinancialActivities":8133577000.0,"changesInCashAndCashEquivalents":464333000.0,"previousYearAsset":56935226000.0,"previousYearSales":47588160000.0,"previousYearNetIncome":1772218000.0,"averageAge":41.6,"averageYearsOfService":13.2,"averageAnnualSalary":7081000.0,"outstandingShares":12739696.0,"dividendPerShare":6.0,"grossProfit2":7287543000.0,"grossProfitMargin":0.158454241,"operatingProfitMargin":0.009518983,"recurringProfitRatio":0.014887957,"SGAtoSalesRatio":0.148935236,"totalAssetTurnover":0.720192915,"currentRatio":1.097906044,"salesRateOfChange":-0.033552316,"netIncomeRageOfChange":-0.747734195,"averageAssetsThisYear":60397576500.0,"totalAssetOrdinaryRateOfReturn":0.011336862," totalAssetNetProfitMargin":0.007402118,"totalAssetsNetProfitmarginAttributableToOwnersOfTheParentCompany":0.007128846,"equityCapital":17507915000.0,"interestBearingDebt":21642408000.0,"companyName":"栗林商船","industry":"海運業"},{"edinetCode":"E04254","stockCode":"9171","submitDate":"2021\/6\/29","endDate":"2021\/3\/31","numberOfEmployee":1103.0,"averageTemporaryStaff":null,"sharesOwned":7906000.0,"sharesOwendPercent":0.621,"numberOfSubsidiary":13.0,"bps":1533.85,"equityRatio":0.282,"cashAndCashEquivalents":9091288000.0,"assets":68834411000.0,"currentAssets":19284514000.0,"fixedAsset":49540219000.0,"tangibleFixedAssets":36338961000.0,"intangibleFixedAssets":1251317000.0,"investmentAndOtherAssets":11949940000.0,"liabilities":46268026000.0,"currentLiabilities":17459283000.0,"shorTermDept":5380000000.0,"currentPortionOfBonds":164000000.0,"currentPortionOfLongTermDebt":2830028000.0,"fixedLiabilities":28808743000.0,"bonds":876000000.0,"convertibleBond":null,"commercialPaper":null,"longTermDebts":11629917000.0,"netAsset":22566384000.0,"capitalStock":15972921000.0,"capital":1215035000.0,"capitalSurplus":978012000.0,"accumulatedEarnings":13800653000.0,"treasuryStock":-20780000.0,"valuationAndConversionAdjustments":3452173000.0,"Sales":41498486000.0,"costOfSales":35412207000.0,"grossProfit":6086279000.0,"sgaExpenses":6127365000.0,"salaryAndBenefit":null,"depreciationAndSGA":359238000.0,"RDExpenses":null,"operatingIncome":-41086000.0,"nonOperatingIncome":723705000.0,"nonOperatingExpenses":377429000.0,"interestExpense":284291000.0,"ordinaryProfit":305189000.0,"extraordinaryGain":788483000.0,"extraordinaryLoss":244574000.0,"incomeBeforeTax":849099000.0,"incomeTaxes":127630000.0,"netIncome":721469000.0,"netIncomeAttributableToOwnersOfTheParentCompany":670662000.0,"comprehensiveIncome":2068484000.0,"eps":53.0,"dilutedEps":null,"per":7.2,"roe":0.036,"cashFlowFromOperatingActivities":3527975000.0,"depreciationAndCashflowFromOperatingActivities":2845672000.0,"cashFlowFromInvestingActivities":-5157644000.0,"cashFlowFromFinancialActivities":2587686000.0,"changesInCashAndCashEquivalents":971141000.0,"previousYearAsset":63859927000.0,"previousYearSales":45991467000.0,"previousYearNetIncome":447070000.0,"averageAge":41.2,"averageYearsOfService":12.3,"averageAnnualSalary":6662000.0,"outstandingShares":12739696.0,"dividendPerShare":6.0,"grossProfit2":6086279000.0,"grossProfitMargin":0.146662676,"operatingProfitMargin":-0.00099006,"recurringProfitRatio":0.00735422,"SGAtoSalesRatio":0.147652736,"totalAssetTurnover":0.602874135,"currentRatio":1.104542151,"salesRateOfChange":-0.097691622,"netIncomeRageOfChange":0.613771893,"averageAssetsThisYear":66347169000.0,"totalAssetOrdinaryRateOfReturn":0.00459988," totalAssetNetProfitMargin":0.010874149,"totalAssetsNetProfitmarginAttributableToOwnersOfTheParentCompany":0.010108374,"equityCapital":19425094000.0,"interestBearingDebt":20879945000.0,"companyName":"栗林商船","industry":"海運業"}]