[{"edinetCode":"E03342","stockCode":"9441","submitDate":"2017\/3\/28","endDate":"2016\/12\/31","numberOfEmployee":1300.0,"averageTemporaryStaff":603.0,"sharesOwned":5991500.0,"sharesOwendPercent":0.8899,"numberOfSubsidiary":1.0,"bps":2759.37,"equityRatio":0.52,"cashAndCashEquivalents":15223568000.0,"assets":34021399000.0,"currentAssets":30365352000.0,"fixedAsset":3656046000.0,"tangibleFixedAssets":983744000.0,"intangibleFixedAssets":311212000.0,"investmentAndOtherAssets":2361088000.0,"liabilities":16100022000.0,"currentLiabilities":10259890000.0,"shorTermDept":14802000.0,"currentPortionOfBonds":null,"currentPortionOfLongTermDebt":null,"fixedLiabilities":5840131000.0,"bonds":null,"convertibleBond":null,"commercialPaper":null,"longTermDebts":5000000000.0,"netAsset":17921376000.0,"capitalStock":17692853000.0,"capital":1148322000.0,"capitalSurplus":1872489000.0,"accumulatedEarnings":15282820000.0,"treasuryStock":-610779000.0,"valuationAndConversionAdjustments":5097000.0,"Sales":89629379000.0,"costOfSales":70954488000.0,"grossProfit":18674890000.0,"sgaExpenses":15828775000.0,"salaryAndBenefit":null,"depreciationAndSGA":276317000.0,"RDExpenses":null,"operatingIncome":2846114000.0,"nonOperatingIncome":94833000.0,"nonOperatingExpenses":13755000.0,"interestExpense":6822000.0,"ordinaryProfit":2927192000.0,"extraordinaryGain":3912000.0,"extraordinaryLoss":127397000.0,"incomeBeforeTax":2803707000.0,"incomeTaxes":1158827000.0,"netIncome":1644879000.0,"netIncomeAttributableToOwnersOfTheParentCompany":1644879000.0,"comprehensiveIncome":1654474000.0,"eps":256.46,"dilutedEps":252.85,"per":11.2,"roe":0.097,"cashFlowFromOperatingActivities":1013435000.0,"depreciationAndCashflowFromOperatingActivities":276317000.0,"cashFlowFromInvestingActivities":-459656000.0,"cashFlowFromFinancialActivities":4821935000.0,"changesInCashAndCashEquivalents":5375714000.0,"previousYearAsset":30204762000.0,"previousYearSales":90145118000.0,"previousYearNetIncome":1798597000.0,"averageAge":null,"averageYearsOfService":null,"averageAnnualSalary":null,"outstandingShares":6732600.0,"dividendPerShare":30.0,"grossProfit2":18674891000.0,"grossProfitMargin":0.208356805,"operatingProfitMargin":0.031754253,"recurringProfitRatio":0.032658845,"SGAtoSalesRatio":0.176602529,"totalAssetTurnover":2.634500098,"currentRatio":2.959617696,"salesRateOfChange":-0.005721208,"netIncomeRageOfChange":-0.085465505,"averageAssetsThisYear":32113080500.0,"totalAssetOrdinaryRateOfReturn":0.091152638," totalAssetNetProfitMargin":0.051221464,"totalAssetsNetProfitmarginAttributableToOwnersOfTheParentCompany":0.051221464,"equityCapital":17697950000.0,"interestBearingDebt":5014802000.0,"companyName":"ベルパーク","industry":"情報・通信業"},{"edinetCode":"E03342","stockCode":"9441","submitDate":"2018\/3\/28","endDate":"2017\/12\/31","numberOfEmployee":1351.0,"averageTemporaryStaff":503.0,"sharesOwned":6029000.0,"sharesOwendPercent":0.8955,"numberOfSubsidiary":1.0,"bps":3064.6,"equityRatio":0.509,"cashAndCashEquivalents":16467267000.0,"assets":38589624000.0,"currentAssets":34887253000.0,"fixedAsset":3702371000.0,"tangibleFixedAssets":1079259000.0,"intangibleFixedAssets":166613000.0,"investmentAndOtherAssets":2456497000.0,"liabilities":18933938000.0,"currentLiabilities":12985955000.0,"shorTermDept":null,"currentPortionOfBonds":null,"currentPortionOfLongTermDebt":null,"fixedLiabilities":5947982000.0,"bonds":null,"convertibleBond":null,"commercialPaper":null,"longTermDebts":5014802000.0,"netAsset":19655685000.0,"capitalStock":19650745000.0,"capital":1148322000.0,"capitalSurplus":1872489000.0,"accumulatedEarnings":17240712000.0,"treasuryStock":-610779000.0,"valuationAndConversionAdjustments":4940000.0,"Sales":88894393000.0,"costOfSales":70341262000.0,"grossProfit":18553130000.0,"sgaExpenses":15401828000.0,"salaryAndBenefit":null,"depreciationAndSGA":239324000.0,"RDExpenses":null,"operatingIncome":3151302000.0,"nonOperatingIncome":46081000.0,"nonOperatingExpenses":12891000.0,"interestExpense":7719000.0,"ordinaryProfit":3184492000.0,"extraordinaryGain":286596000.0,"extraordinaryLoss":250302000.0,"incomeBeforeTax":3220786000.0,"incomeTaxes":1038413000.0,"netIncome":2182373000.0,"netIncomeAttributableToOwnersOfTheParentCompany":2182373000.0,"comprehensiveIncome":2182216000.0,"eps":340.26,"dilutedEps":null,"per":10.0,"roe":0.117,"cashFlowFromOperatingActivities":2004690000.0,"depreciationAndCashflowFromOperatingActivities":239324000.0,"cashFlowFromInvestingActivities":-536455000.0,"cashFlowFromFinancialActivities":-224536000.0,"changesInCashAndCashEquivalents":1243698000.0,"previousYearAsset":34021399000.0,"previousYearSales":89629379000.0,"previousYearNetIncome":1644879000.0,"averageAge":null,"averageYearsOfService":null,"averageAnnualSalary":null,"outstandingShares":6732600.0,"dividendPerShare":55.0,"grossProfit2":18553131000.0,"grossProfitMargin":0.2087098,"operatingProfitMargin":0.035449952,"recurringProfitRatio":0.035823317,"SGAtoSalesRatio":0.173259837,"totalAssetTurnover":2.303582771,"currentRatio":2.68653734,"salesRateOfChange":-0.00820028,"netIncomeRageOfChange":0.326768109,"averageAssetsThisYear":36305511500.0,"totalAssetOrdinaryRateOfReturn":0.087713735," totalAssetNetProfitMargin":0.060111341,"totalAssetsNetProfitmarginAttributableToOwnersOfTheParentCompany":0.060111341,"equityCapital":19655685000.0,"interestBearingDebt":5014802000.0,"companyName":"ベルパーク","industry":"情報・通信業"},{"edinetCode":"E03342","stockCode":"9441","submitDate":"2019\/3\/26","endDate":"2018\/12\/31","numberOfEmployee":1489.0,"averageTemporaryStaff":468.0,"sharesOwned":6068000.0,"sharesOwendPercent":0.9461,"numberOfSubsidiary":1.0,"bps":3326.57,"equityRatio":0.546,"cashAndCashEquivalents":14872542000.0,"assets":39093397000.0,"currentAssets":34910154000.0,"fixedAsset":4183242000.0,"tangibleFixedAssets":1454712000.0,"intangibleFixedAssets":232299000.0,"investmentAndOtherAssets":2496230000.0,"liabilities":17757762000.0,"currentLiabilities":12121181000.0,"shorTermDept":null,"currentPortionOfBonds":null,"currentPortionOfLongTermDebt":null,"fixedLiabilities":5636581000.0,"bonds":null,"convertibleBond":null,"commercialPaper":null,"longTermDebts":5014802000.0,"netAsset":21335634000.0,"capitalStock":21329708000.0,"capital":1148322000.0,"capitalSurplus":1872489000.0,"accumulatedEarnings":18920044000.0,"treasuryStock":-611148000.0,"valuationAndConversionAdjustments":5926000.0,"Sales":98088102000.0,"costOfSales":78112218000.0,"grossProfit":19975884000.0,"sgaExpenses":16746615000.0,"salaryAndBenefit":null,"depreciationAndSGA":265372000.0,"RDExpenses":null,"operatingIncome":3229269000.0,"nonOperatingIncome":37952000.0,"nonOperatingExpenses":10257000.0,"interestExpense":8787000.0,"ordinaryProfit":3256964000.0,"extraordinaryGain":17501000.0,"extraordinaryLoss":151554000.0,"incomeBeforeTax":3122911000.0,"incomeTaxes":1007444000.0,"netIncome":2115466000.0,"netIncomeAttributableToOwnersOfTheParentCompany":2115466000.0,"comprehensiveIncome":2116452000.0,"eps":329.83,"dilutedEps":null,"per":11.9,"roe":0.103,"cashFlowFromOperatingActivities":-170119000.0,"depreciationAndCashflowFromOperatingActivities":265372000.0,"cashFlowFromInvestingActivities":-988138000.0,"cashFlowFromFinancialActivities":-436467000.0,"changesInCashAndCashEquivalents":-1594725000.0,"previousYearAsset":38589624000.0,"previousYearSales":88894393000.0,"previousYearNetIncome":2182373000.0,"averageAge":null,"averageYearsOfService":null,"averageAnnualSalary":null,"outstandingShares":6732600.0,"dividendPerShare":70.0,"grossProfit2":19975884000.0,"grossProfitMargin":0.203652467,"operatingProfitMargin":0.032922127,"recurringProfitRatio":0.033204476,"SGAtoSalesRatio":0.17073034,"totalAssetTurnover":2.509070829,"currentRatio":2.8800951,"salesRateOfChange":0.103422822,"netIncomeRageOfChange":-0.030657912,"averageAssetsThisYear":38841510500.0,"totalAssetOrdinaryRateOfReturn":0.083852661," totalAssetNetProfitMargin":0.054464051,"totalAssetsNetProfitmarginAttributableToOwnersOfTheParentCompany":0.054464051,"equityCapital":21335634000.0,"interestBearingDebt":5014802000.0,"companyName":"ベルパーク","industry":"情報・通信業"},{"edinetCode":"E03342","stockCode":"9441","submitDate":"2020\/3\/24","endDate":"2019\/12\/31","numberOfEmployee":1666.0,"averageTemporaryStaff":472.0,"sharesOwned":6080500.0,"sharesOwendPercent":0.9481,"numberOfSubsidiary":1.0,"bps":3724.78,"equityRatio":0.548,"cashAndCashEquivalents":21345930000.0,"assets":43572868000.0,"currentAssets":38087747000.0,"fixedAsset":5485120000.0,"tangibleFixedAssets":1780791000.0,"intangibleFixedAssets":573084000.0,"investmentAndOtherAssets":3131245000.0,"liabilities":19683618000.0,"currentLiabilities":13982832000.0,"shorTermDept":null,"currentPortionOfBonds":null,"currentPortionOfLongTermDebt":null,"fixedLiabilities":5700786000.0,"bonds":null,"convertibleBond":null,"commercialPaper":null,"longTermDebts":5014802000.0,"netAsset":23889250000.0,"capitalStock":23888987000.0,"capital":1148322000.0,"capitalSurplus":1872489000.0,"accumulatedEarnings":21479691000.0,"treasuryStock":-611515000.0,"valuationAndConversionAdjustments":262000.0,"Sales":103304000000.0,"costOfSales":79137825000.0,"grossProfit":24165780000.0,"sgaExpenses":19790207000.0,"salaryAndBenefit":null,"depreciationAndSGA":296891000.0,"RDExpenses":null,"operatingIncome":4375573000.0,"nonOperatingIncome":37856000.0,"nonOperatingExpenses":34184000.0,"interestExpense":8427000.0,"ordinaryProfit":4379245000.0,"extraordinaryGain":40067000.0,"extraordinaryLoss":78268000.0,"incomeBeforeTax":4341043000.0,"incomeTaxes":1300370000.0,"netIncome":3040672000.0,"netIncomeAttributableToOwnersOfTheParentCompany":3040672000.0,"comprehensiveIncome":3035008000.0,"eps":474.09,"dilutedEps":null,"per":9.2,"roe":0.134,"cashFlowFromOperatingActivities":8584957000.0,"depreciationAndCashflowFromOperatingActivities":296891000.0,"cashFlowFromInvestingActivities":-1630463000.0,"cashFlowFromFinancialActivities":-481105000.0,"changesInCashAndCashEquivalents":6473388000.0,"previousYearAsset":39093397000.0,"previousYearSales":98088102000.0,"previousYearNetIncome":2115466000.0,"averageAge":30.2,"averageYearsOfService":5.1,"averageAnnualSalary":4607430.0,"outstandingShares":6732600.0,"dividendPerShare":119.0,"grossProfit2":24165780000.0,"grossProfitMargin":0.233929687,"operatingProfitMargin":0.042356441,"recurringProfitRatio":0.042391986,"SGAtoSalesRatio":0.191573247,"totalAssetTurnover":2.370824087,"currentRatio":2.723893629,"salesRateOfChange":0.053171617,"netIncomeRageOfChange":0.437353283,"averageAssetsThisYear":41333132500.0,"totalAssetOrdinaryRateOfReturn":0.105949991," totalAssetNetProfitMargin":0.073565003,"totalAssetsNetProfitmarginAttributableToOwnersOfTheParentCompany":0.073565003,"equityCapital":23889249000.0,"interestBearingDebt":5014802000.0,"companyName":"ベルパーク","industry":"情報・通信業"},{"edinetCode":"E03342","stockCode":"9441","submitDate":"2021\/3\/24","endDate":"2020\/12\/31","numberOfEmployee":1855.0,"averageTemporaryStaff":447.0,"sharesOwned":6094400.0,"sharesOwendPercent":0.9502,"numberOfSubsidiary":1.0,"bps":4157.04,"equityRatio":0.575,"cashAndCashEquivalents":22042949000.0,"assets":46371852000.0,"currentAssets":40420106000.0,"fixedAsset":5951746000.0,"tangibleFixedAssets":1993251000.0,"intangibleFixedAssets":472668000.0,"investmentAndOtherAssets":3485826000.0,"liabilities":19710250000.0,"currentLiabilities":18980183000.0,"shorTermDept":null,"currentPortionOfBonds":null,"currentPortionOfLongTermDebt":5014802000.0,"fixedLiabilities":730066000.0,"bonds":null,"convertibleBond":null,"commercialPaper":null,"longTermDebts":null,"netAsset":26661602000.0,"capitalStock":26598513000.0,"capital":1148322000.0,"capitalSurplus":1872489000.0,"accumulatedEarnings":24189217000.0,"treasuryStock":-611515000.0,"valuationAndConversionAdjustments":63088000.0,"Sales":98843080000.0,"costOfSales":74493294000.0,"grossProfit":24349785000.0,"sgaExpenses":19297152000.0,"salaryAndBenefit":null,"depreciationAndSGA":331674000.0,"RDExpenses":null,"operatingIncome":5052632000.0,"nonOperatingIncome":306573000.0,"nonOperatingExpenses":11145000.0,"interestExpense":7594000.0,"ordinaryProfit":5348060000.0,"extraordinaryGain":73831000.0,"extraordinaryLoss":47458000.0,"incomeBeforeTax":5374433000.0,"incomeTaxes":1754175000.0,"netIncome":3620257000.0,"netIncomeAttributableToOwnersOfTheParentCompany":3620257000.0,"comprehensiveIncome":3683084000.0,"eps":564.47,"dilutedEps":null,"per":12.2,"roe":0.143,"cashFlowFromOperatingActivities":2425680000.0,"depreciationAndCashflowFromOperatingActivities":331674000.0,"cashFlowFromInvestingActivities":-818105000.0,"cashFlowFromFinancialActivities":-910555000.0,"changesInCashAndCashEquivalents":697018000.0,"previousYearAsset":43572868000.0,"previousYearSales":103304000000.0,"previousYearNetIncome":3040672000.0,"averageAge":30.4,"averageYearsOfService":5.3,"averageAnnualSalary":4602393.0,"outstandingShares":6732600.0,"dividendPerShare":170.0,"grossProfit2":24349786000.0,"grossProfitMargin":0.246347908,"operatingProfitMargin":0.051117711,"recurringProfitRatio":0.05410657,"SGAtoSalesRatio":0.195230177,"totalAssetTurnover":2.131531861,"currentRatio":2.129595168,"salesRateOfChange":-0.043178793,"netIncomeRageOfChange":0.190610826,"averageAssetsThisYear":44972360000.0,"totalAssetOrdinaryRateOfReturn":0.11891882," totalAssetNetProfitMargin":0.0804996,"totalAssetsNetProfitmarginAttributableToOwnersOfTheParentCompany":0.0804996,"equityCapital":26661601000.0,"interestBearingDebt":5014802000.0,"companyName":"ベルパーク","industry":"情報・通信業"},{"edinetCode":"E03342","stockCode":"9441","submitDate":"2022\/3\/24","endDate":"2021\/12\/31","numberOfEmployee":1883.0,"averageTemporaryStaff":441.0,"sharesOwned":6127600.0,"sharesOwendPercent":0.9554,"numberOfSubsidiary":1.0,"bps":1495.33,"equityRatio":0.663,"cashAndCashEquivalents":18331617000.0,"assets":43366826000.0,"currentAssets":37000444000.0,"fixedAsset":6366382000.0,"tangibleFixedAssets":2100332000.0,"intangibleFixedAssets":529503000.0,"investmentAndOtherAssets":3736546000.0,"liabilities":14595527000.0,"currentLiabilities":13806948000.0,"shorTermDept":14802000.0,"currentPortionOfBonds":null,"currentPortionOfLongTermDebt":null,"fixedLiabilities":788578000.0,"bonds":null,"convertibleBond":null,"commercialPaper":null,"longTermDebts":null,"netAsset":28771299000.0,"capitalStock":28740720000.0,"capital":1148322000.0,"capitalSurplus":1872489000.0,"accumulatedEarnings":26331424000.0,"treasuryStock":-611515000.0,"valuationAndConversionAdjustments":30578000.0,"Sales":107282000000.0,"costOfSales":81798061000.0,"grossProfit":25483830000.0,"sgaExpenses":20806107000.0,"salaryAndBenefit":null,"depreciationAndSGA":343712000.0,"RDExpenses":null,"operatingIncome":4677723000.0,"nonOperatingIncome":80407000.0,"nonOperatingExpenses":111895000.0,"interestExpense":1657000.0,"ordinaryProfit":4646235000.0,"extraordinaryGain":183075000.0,"extraordinaryLoss":155554000.0,"incomeBeforeTax":4673756000.0,"incomeTaxes":1396341000.0,"netIncome":3277414000.0,"netIncomeAttributableToOwnersOfTheParentCompany":3277414000.0,"comprehensiveIncome":3244904000.0,"eps":170.34,"dilutedEps":null,"per":15.1,"roe":0.118,"cashFlowFromOperatingActivities":3673444000.0,"depreciationAndCashflowFromOperatingActivities":343712000.0,"cashFlowFromInvestingActivities":-1250089000.0,"cashFlowFromFinancialActivities":-6134686000.0,"changesInCashAndCashEquivalents":-3711331000.0,"previousYearAsset":46371852000.0,"previousYearSales":98843080000.0,"previousYearNetIncome":3620257000.0,"averageAge":31.4,"averageYearsOfService":5.8,"averageAnnualSalary":4814871.0,"outstandingShares":6732600.0,"dividendPerShare":154.0,"grossProfit2":25483831000.0,"grossProfitMargin":0.237540842,"operatingProfitMargin":0.043602167,"recurringProfitRatio":0.04330866,"SGAtoSalesRatio":0.193938666,"totalAssetTurnover":2.473823932,"currentRatio":2.679842352,"salesRateOfChange":0.08537585,"netIncomeRageOfChange":-0.094701288,"averageAssetsThisYear":44869339000.0,"totalAssetOrdinaryRateOfReturn":0.103550333," totalAssetNetProfitMargin":0.07304351,"totalAssetsNetProfitmarginAttributableToOwnersOfTheParentCompany":0.07304351,"equityCapital":28771298000.0,"interestBearingDebt":14802000.0,"companyName":"ベルパーク","industry":"情報・通信業"}]